setup.py
pipeliner/__init__.py
pipeliner/context.py
pipeliner/exceptions.py
pipeliner/register.py
pipeliner.egg-info/PKG-INFO
pipeliner.egg-info/SOURCES.txt
pipeliner.egg-info/dependency_links.txt
pipeliner.egg-info/requires.txt
pipeliner.egg-info/top_level.txt
pipeliner.egg-info/zip-safe
pipeliner/pipeline/__init__.py
pipeliner/pipeline/pipeline.py
pipeliner/pipeline/backend/__init__.py
pipeliner/pipeline/backend/abstract.py
pipeliner/pipeline/backend/gevent_backend.py