Metadata-Version: 1.0
Name: pipeliner
Version: 0.0.4
Summary: Task execution framework with dependencies control
Home-page: UNKNOWN
Author: Nikolay Sedelnikov
Author-email: n.sedelnikov@gmail.com
License: UNKNOWN
Platform: UNKNOWN
